django_generic_model_fields/__init__.py
django_generic_model_fields/create_generic_blob.py
django_generic_model_fields/create_generic_boolean.py
django_generic_model_fields/create_generic_date.py
django_generic_model_fields/create_generic_datetime.py
django_generic_model_fields/create_generic_decimal.py
django_generic_model_fields/create_generic_enum.py
django_generic_model_fields/create_generic_fk.py
django_generic_model_fields/create_generic_integer.py
django_generic_model_fields/create_generic_m2m.py
django_generic_model_fields/create_generic_one_to_one_fk.py
django_generic_model_fields/create_generic_text.py
django_generic_model_fields/create_generic_uuid.py
django_generic_model_fields/create_generic_varchar.py
django_generic_model_fields-2.0.0.dist-info/LICENSE
django_generic_model_fields-2.0.0.dist-info/METADATA
django_generic_model_fields-2.0.0.dist-info/WHEEL
django_generic_model_fields-2.0.0.dist-info/top_level.txt
django_generic_model_fields-2.0.0.dist-info/RECORD
