Metadata-Version: 2.2
Name: django-generic-model-fields
Version: 2.0.0
Summary: Sensible Django model fields for easy migrations and database portability
Home-page: https://github.com/iBfuRsiFUBbfzPdnJhXUfFFkk/django-generic-model-fields
Author: WaAWsUPQpGcRLcLcEkthyDyhX
Author-email: molding_exact_6i@icloud.com
Classifier: Programming Language :: Python :: 3
Classifier: Framework :: Django
Classifier: License :: OSI Approved :: MIT License
Classifier: Operating System :: OS Independent
Requires-Python: >=3.11
License-File: LICENSE
Requires-Dist: django==5.1.7
Dynamic: author
Dynamic: author-email
Dynamic: classifier
Dynamic: description
Dynamic: description-content-type
Dynamic: home-page
Dynamic: requires-dist
Dynamic: requires-python
Dynamic: summary
